{
  "instructors": [
    {
      "id": 1,
      "avatar_url": "https://source.unsplash.com/collection/633568/500x500",
      "name": "Henryque",
      "birth": 925171200000,
      "gender": "M",
      "services": "Crossfit, Natação, Musculação",
      "created_at": 1604330138983
    },
    {
      "id": 2,
      "avatar_url": "https://www.youtube.com/watch?v=qn67xPzc1CA&ab_channel=ManuelStagars",
      "name": "Felype",
      "birth": 875491200000,
      "gender": "M",
      "services": "Natação, Crossfit",
      "created_at": 1604330165341
    },
    {
      "id": 3,
      "avatar_url": "https://www.youtube.com/watch?v=r5tz4VpTeL4&ab_channel=Rocketseat",
      "name": "Ariely",
      "birth": 739065600000,
      "gender": "F",
      "services": "Musculação",
      "created_at": 1604330445982
    },
    {
      "id": 4,
      "avatar_url": "https://www.youtube.com/watch?v=J6rVaFzOEP8&ab_channel=TraversyMedia",
      "name": "Paula",
      "birth": 625881600000,
      "gender": "F",
      "services": "Crossfit, Natação",
      "created_at": 1604972905978
    },
    {
      "id": 5,
      "avatar_url": "https://www.youtube.com/watch?v=J6rVaFzOEP8&ab_channel=TraversyMedia",
      "name": "Laissa",
      "birth": 628387200000,
      "gender": "F",
      "services": "Natação",
      "created_at": 1604972989878
    },
    {
      "id": 6,
      "avatar_url": "https://www.youtube.com/watch?v=qn67xPzc1CA&ab_channel=ManuelStagars",
      "name": "Amelie",
      "birth": 925171200000,
      "gender": "F",
      "services": "Crossfit",
      "created_at": 1605363002002
    },
    {
      "id": 7,
      "avatar_url": "https://www.youtube.com/watch?v=NJBKdNAPGbk&ab_channel=Mr_MoMoMusic",
      "name": "Karine",
      "birth": 913420800000,
      "gender": "F",
      "services": "Natação",
      "created_at": 1605364499604
    },
    {
      "id": 8,
      "avatar_url": "https://www.youtube.com/watch?v=NJBKdNAPGbk&ab_channel=Mr_MoMoMusic",
      "name": "Fernanda",
      "birth": 913420800000,
      "gender": "F",
      "services": "Crossfit",
      "created_at": 1605364572720
    },
    {
      "id": 9,
      "avatar_url": "https://www.youtube.com/watch?v=NJBKdNAPGbk&ab_channel=Mr_MoMoMusic",
      "name": "Karine",
      "birth": 944956800000,
      "gender": "F",
      "services": "Natação",
      "created_at": 1605364739113
    },
    {
      "id": 10,
      "avatar_url": "https://www.youtube.com/watch?v=NJBKdNAPGbk&ab_channel=Mr_MoMoMusic",
      "name": "Karine Sousa",
      "birth": 944956800000,
      "gender": "F",
      "services": "Natação, Crossfit",
      "created_at": 1605364799760
    }
  ]
}